novacore/__init__.py
novacore/license.py
novacore-2.5.0.dist-info/licenses/LICENSE
novacore-2.5.0.dist-info/METADATA
novacore-2.5.0.dist-info/WHEEL
novacore-2.5.0.dist-info/entry_points.txt
novacore-2.5.0.dist-info/top_level.txt
novacore-2.5.0.dist-info/RECORD
