Metadata-Version: 2.4
Name: novacore
Version: 2.5.0
Summary: License validation for Phantom Licensing System
Author-email: Vedant <vedant.storm@gmail.com>
License: Mozilla Public License 2.0
Project-URL: Homepage, https://github.com/VedantStorm/NovaCore
Project-URL: Repository, https://github.com/VedantStorm/NovaCore
Project-URL: Issues, https://github.com/VedantStorm/NovaCore/issues
Project-URL: Documentation, https://github.com/VedantStorm/NovaCore#readme
Keywords: license,phantom,verification,api,novacore,license-check
Classifier: Development Status :: 5 - Production/Stable
Classifier: Intended Audience :: Developers
Classifier: Programming Language :: Python :: 3
Classifier: Programming Language :: Python :: 3.9
Classifier: Programming Language :: Python :: 3.10
Classifier: Programming Language :: Python :: 3.11
Classifier: Programming Language :: Python :: 3.12
Classifier: License :: OSI Approved :: Mozilla Public License 2.0 (MPL 2.0)
Classifier: Operating System :: OS Independent
Classifier: Topic :: Software Development :: Libraries
Classifier: Topic :: Software Development :: Build Tools
Requires-Python: >=3.9
License-File: LICENSE
Requires-Dist: requests>=2.31
Dynamic: license-file
